pyband/__init__.py
pyband/client.py
pyband/constants.py
pyband/cosmos_app.py
pyband/data.py
pyband/exceptions.py
pyband/messages/__init__.py
pyband/messages/base.py
pyband/messages/cosmos/__init__.py
pyband/messages/cosmos/bank/__init__.py
pyband/messages/cosmos/bank/v1beta1/__init__.py
pyband/messages/cosmos/bank/v1beta1/msgs.py
pyband/messages/cosmos/distribution/__init__.py
pyband/messages/cosmos/distribution/v1beta1/__init__.py
pyband/messages/cosmos/distribution/v1beta1/msgs.py
pyband/messages/cosmos/gov/__init__.py
pyband/messages/cosmos/gov/v1beta1/__init__.py
pyband/messages/cosmos/gov/v1beta1/msgs.py
pyband/messages/cosmos/staking/__init__.py
pyband/messages/cosmos/staking/v1beta1/__init__.py
pyband/messages/cosmos/staking/v1beta1/msgs.py
pyband/messages/oracle/__init__.py
pyband/messages/oracle/v1/__init__.py
pyband/messages/oracle/v1/msgs.py
pyband/obi.py
pyband/proto/__init__.py
pyband/proto/cosmos/__init__.py
pyband/proto/cosmos/auth/__init__.py
pyband/proto/cosmos/auth/v1beta1/__init__.py
pyband/proto/cosmos/authz/__init__.py
pyband/proto/cosmos/authz/v1beta1/__init__.py
pyband/proto/cosmos/bank/__init__.py
pyband/proto/cosmos/bank/v1beta1/__init__.py
pyband/proto/cosmos/base/__init__.py
pyband/proto/cosmos/base/abci/__init__.py
pyband/proto/cosmos/base/abci/v1beta1/__init__.py
pyband/proto/cosmos/base/kv/__init__.py
pyband/proto/cosmos/base/kv/v1beta1/__init__.py
pyband/proto/cosmos/base/query/__init__.py
pyband/proto/cosmos/base/query/v1beta1/__init__.py
pyband/proto/cosmos/base/reflection/__init__.py
pyband/proto/cosmos/base/reflection/v1beta1/__init__.py
pyband/proto/cosmos/base/reflection/v2alpha1/__init__.py
pyband/proto/cosmos/base/snapshots/__init__.py
pyband/proto/cosmos/base/snapshots/v1beta1/__init__.py
pyband/proto/cosmos/base/store/__init__.py
pyband/proto/cosmos/base/store/v1beta1/__init__.py
pyband/proto/cosmos/base/tendermint/__init__.py
pyband/proto/cosmos/base/tendermint/v1beta1/__init__.py
pyband-0.3.5.dist-info/WHEEL
pyband-0.3.5.dist-info/METADATA
pyband-0.3.5.dist-info/RECORD
