Metadata-Version: 2.1
Name: pyband
Version: 0.3.5
Summary: Python library for BandChain
Home-page: https://bandprotocol.com/
License: MIT
Keywords: BAND,BLOCKCHAIN,ORACLE
Author: Band Protocol
Requires-Python: >=3.7,<4.0
Classifier: Development Status :: 3 - Alpha
Classifier: Intended Audience :: Developers
Classifier: License :: OSI Approved :: MIT License
Classifier: Programming Language :: Python :: 3
Classifier: Programming Language :: Python :: 3.7
Classifier: Programming Language :: Python :: 3.8
Classifier: Programming Language :: Python :: 3.9
Classifier: Programming Language :: Python :: 3.10
Classifier: Programming Language :: Python :: 3.11
Classifier: Programming Language :: Python :: 3
Classifier: Programming Language :: Python :: 3.6
Classifier: Programming Language :: Python :: 3.7
Classifier: Programming Language :: Python :: 3.8
Requires-Dist: bech32 (==1.2.0)
Requires-Dist: betterproto (==2.0.0b5)
Requires-Dist: bip32 (==0.0.8)
Requires-Dist: ecdsa (==0.15)
Requires-Dist: grpclib (==0.4.3)
Requires-Dist: ledgerblue (>=0.1.45,<0.2.0)
Requires-Dist: mnemonic (==0.19)
Requires-Dist: python-dateutil (==2.8.2)
Project-URL: Documentation, https://docs.bandchain.org/client-library/pyband/getting-started.html
Project-URL: Repository, https://github.com/bandprotocol/pyband
